port_checker.py
new_port_checker-1.0.4.dist-info/METADATA
new_port_checker-1.0.4.dist-info/WHEEL
new_port_checker-1.0.4.dist-info/entry_points.txt
new_port_checker-1.0.4.dist-info/top_level.txt
new_port_checker-1.0.4.dist-info/RECORD
