Metadata-Version: 2.1
Name: new-port-checker
Version: 1.0.4
Summary: A Python tool for checking port availability
Home-page: https://github.com/yourusername/new_port_checker
Author: liuxiaojian
Author-email: 107773270@qq.com
License: UNKNOWN
Platform: UNKNOWN
Classifier: Programming Language :: Python :: 3
Classifier: License :: OSI Approved :: MIT License
Classifier: Operating System :: OS Independent
Requires-Python: >=3.6
